my_library/__init__.py
my_library/example.py
keerthan_library-0.1.1.dist-info/LICENSE
keerthan_library-0.1.1.dist-info/METADATA
keerthan_library-0.1.1.dist-info/WHEEL
keerthan_library-0.1.1.dist-info/top_level.txt
keerthan_library-0.1.1.dist-info/RECORD
