Metadata-Version: 2.1
Name: keerthan-library
Version: 0.1.1
Summary: A sample Python library for demonstration
Home-page: https://github.com/keerthan156/my-library
Author: keerthan
Author-email: keerthankeerthi32@gmail.com
Classifier: Programming Language :: Python :: 3
Classifier: License :: OSI Approved :: MIT License
Classifier: Operating System :: OS Independent
Requires-Python: >=3.6
License-File: LICENSE
